odoo/addons/base_currency_iso_4217/README.rst
odoo/addons/base_currency_iso_4217/__init__.py
odoo/addons/base_currency_iso_4217/__manifest__.py
odoo/addons/base_currency_iso_4217/data/res_currency_data.xml
odoo/addons/base_currency_iso_4217/i18n/base_currency_iso_4217.pot
odoo/addons/base_currency_iso_4217/i18n/de.po
odoo/addons/base_currency_iso_4217/i18n/es.po
odoo/addons/base_currency_iso_4217/i18n/it.po
odoo/addons/base_currency_iso_4217/i18n/nl.po
odoo/addons/base_currency_iso_4217/models/__init__.py
odoo/addons/base_currency_iso_4217/models/res_currency.py
odoo/addons/base_currency_iso_4217/readme/CONTRIBUTORS.rst
odoo/addons/base_currency_iso_4217/readme/DESCRIPTION.rst
odoo/addons/base_currency_iso_4217/static/description/icon.png
odoo/addons/base_currency_iso_4217/static/description/index.html
odoo/addons/base_currency_iso_4217/views/res_currency_views.xml
odoo14_addon_base_currency_iso_4217-14.0.1.0.1.dev8.dist-info/METADATA
odoo14_addon_base_currency_iso_4217-14.0.1.0.1.dev8.dist-info/WHEEL
odoo14_addon_base_currency_iso_4217-14.0.1.0.1.dev8.dist-info/top_level.txt
odoo14_addon_base_currency_iso_4217-14.0.1.0.1.dev8.dist-info/RECORD
